noise_injection/__init__.py
noise_injection/api/__init__.py
noise_injection/api/context.py
noise_injection/api/functional.py
noise_injection/api/sweep.py
noise_injection/core/__init__.py
noise_injection/core/generators.py
noise_injection/core/noise_layer.py
noise_injection/core/selectors.py
noise_injection/mlx/__init__.py
noise_injection/mlx/generators.py
noise_injection/mlx/noise_layer.py
noise_injection/mlx/sweep.py
noise_injection-0.1.0.dist-info/METADATA
noise_injection-0.1.0.dist-info/WHEEL
noise_injection-0.1.0.dist-info/top_level.txt
noise_injection-0.1.0.dist-info/RECORD
