Metadata-Version: 2.4
Name: noise-injection
Version: 0.1.0
Summary: Memory-efficient weight noise injection for LLMs
Requires-Python: >=3.9
Requires-Dist: torch>=2.0.0
Requires-Dist: transformers>=4.30.0
Requires-Dist: datasets>=2.0.0
Requires-Dist: tqdm>=4.65.0
Requires-Dist: numpy>=1.20.0
Requires-Dist: accelerate>=0.20.0
Requires-Dist: build>=1.4.0
Requires-Dist: twine>=6.2.0
Provides-Extra: examples
Requires-Dist: python-dotenv>=1.0.0; extra == "examples"
Requires-Dist: pyyaml>=6.0; extra == "examples"
Requires-Dist: matplotlib>=3.9.0; extra == "examples"
Provides-Extra: mlx
Requires-Dist: mlx>=0.20.0; extra == "mlx"
Requires-Dist: mlx-lm>=0.19.0; extra == "mlx"
